{"id":"s1IY","dependencies":[{"name":"C:\\Users\\kaan.akturk\\Desktop\\Task\\node_modules\\ol\\package.json","includedInParent":true,"mtime":1534415398404},{"name":"C:\\Users\\kaan.akturk\\Desktop\\Task\\package.json","includedInParent":true,"mtime":1534415877866},{"name":"../render/ReplayType.js","loc":{"line":4,"column":23},"parent":"C:\\Users\\kaan.akturk\\Desktop\\Task\\node_modules\\ol\\render\\replay.js","resolved":"C:\\Users\\kaan.akturk\\Desktop\\Task\\node_modules\\ol\\render\\ReplayType.js"}],"generated":{"js":"\"use strict\";Object.defineProperty(exports,\"__esModule\",{value:!0}),exports.TEXT_ALIGN=exports.ORDER=void 0;var e=require(\"../render/ReplayType.js\"),t=r(e);function r(e){return e&&e.__esModule?e:{default:e}}var a=exports.ORDER=[t.default.POLYGON,t.default.CIRCLE,t.default.LINE_STRING,t.default.IMAGE,t.default.TEXT,t.default.DEFAULT],d=exports.TEXT_ALIGN={};d.left=0,d.end=0,d.center=.5,d.right=1,d.start=1,d.top=0,d.middle=.5,d.hanging=.2,d.alphabetic=.8,d.ideographic=.8,d.bottom=1;","map":{"mappings":[{"source":"node_modules\\ol\\render\\replay.js","original":{"line":37,"column":0},"generated":{"line":1,"column":0}},{"source":"node_modules\\ol\\render\\replay.js","original":{"line":37,"column":0},"generated":{"line":1,"column":13}},{"source":"node_modules\\ol\\render\\replay.js","original":{"line":37,"column":0},"generated":{"line":1,"column":20}},{"source":"node_modules\\ol\\render\\replay.js","original":{"line":37,"column":0},"generated":{"line":1,"column":35}},{"source":"node_modules\\ol\\render\\replay.js","original":{"line":37,"column":0},"generated":{"line":1,"column":43}},{"source":"node_modules\\ol\\render\\replay.js","original":{"line":37,"column":0},"generated":{"line":1,"column":56}},{"source":"node_modules\\ol\\render\\replay.js","original":{"line":37,"column":0},"generated":{"line":1,"column":57}},{"source":"node_modules\\ol\\render\\replay.js","original":{"line":37,"column":0},"generated":{"line":1,"column":64}},{"source":"node_modules\\ol\\render\\replay.js","original":{"line":37,"column":0},"generated":{"line":1,"column":68}},{"source":"node_modules\\ol\\render\\replay.js","original":{"line":37,"column":0},"generated":{"line":1,"column":76}},{"source":"node_modules\\ol\\render\\replay.js","original":{"line":37,"column":0},"generated":{"line":1,"column":87}},{"source":"node_modules\\ol\\render\\replay.js","original":{"line":37,"column":0},"generated":{"line":1,"column":95}},{"source":"node_modules\\ol\\render\\replay.js","original":{"line":37,"column":0},"generated":{"line":1,"column":106}},{"source":"node_modules\\ol\\render\\replay.js","original":{"line":4,"column":0},"generated":{"line":1,"column":108}},{"source":"node_modules\\ol\\render\\replay.js","original":{"line":4,"column":0},"generated":{"line":1,"column":112}},{"source":"node_modules\\ol\\render\\replay.js","original":{"line":4,"column":0},"generated":{"line":1,"column":114}},{"source":"node_modules\\ol\\render\\replay.js","original":{"line":4,"column":0},"generated":{"line":1,"column":122}},{"source":"node_modules\\ol\\render\\replay.js","original":{"line":37,"column":0},"generated":{"line":1,"column":149}},{"source":"node_modules\\ol\\render\\replay.js","original":{"line":37,"column":0},"generated":{"line":1,"column":151}},{"source":"node_modules\\ol\\render\\replay.js","original":{"line":37,"column":0},"generated":{"line":1,"column":153}},{"source":"node_modules\\ol\\render\\replay.js","original":{"line":37,"column":0},"generated":{"line":1,"column":156}},{"source":"node_modules\\ol\\render\\replay.js","original":{"line":37,"column":0},"generated":{"line":1,"column":165}},{"source":"node_modules\\ol\\render\\replay.js","original":{"line":37,"column":0},"generated":{"line":1,"column":167}},{"source":"node_modules\\ol\\render\\replay.js","original":{"line":37,"column":0},"generated":{"line":1,"column":170}},{"source":"node_modules\\ol\\render\\replay.js","original":{"line":37,"column":0},"generated":{"line":1,"column":177}},{"source":"node_modules\\ol\\render\\replay.js","original":{"line":37,"column":0},"generated":{"line":1,"column":180}},{"source":"node_modules\\ol\\render\\replay.js","original":{"line":37,"column":0},"generated":{"line":1,"column":182}},{"source":"node_modules\\ol\\render\\replay.js","original":{"line":37,"column":0},"generated":{"line":1,"column":193}},{"source":"node_modules\\ol\\render\\replay.js","original":{"line":37,"column":0},"generated":{"line":1,"column":195}},{"source":"node_modules\\ol\\render\\replay.js","original":{"line":37,"column":0},"generated":{"line":1,"column":196}},{"source":"node_modules\\ol\\render\\replay.js","original":{"line":37,"column":0},"generated":{"line":1,"column":204}},{"source":"node_modules\\ol\\render\\replay.js","original":{"line":11,"column":7},"generated":{"line":1,"column":207}},{"source":"node_modules\\ol\\render\\replay.js","name":"ORDER","original":{"line":11,"column":11},"generated":{"line":1,"column":211}},{"source":"node_modules\\ol\\render\\replay.js","original":{"line":11,"column":19},"generated":{"line":1,"column":213}},{"source":"node_modules\\ol\\render\\replay.js","original":{"line":11,"column":19},"generated":{"line":1,"column":221}},{"source":"node_modules\\ol\\render\\replay.js","original":{"line":11,"column":19},"generated":{"line":1,"column":227}},{"source":"node_modules\\ol\\render\\replay.js","name":"ReplayType","original":{"line":12,"column":2},"generated":{"line":1,"column":228}},{"source":"node_modules\\ol\\render\\replay.js","name":"POLYGON","original":{"line":12,"column":13},"generated":{"line":1,"column":230}},{"source":"node_modules\\ol\\render\\replay.js","name":"POLYGON","original":{"line":12,"column":13},"generated":{"line":1,"column":238}},{"source":"node_modules\\ol\\render\\replay.js","name":"ReplayType","original":{"line":13,"column":2},"generated":{"line":1,"column":246}},{"source":"node_modules\\ol\\render\\replay.js","name":"CIRCLE","original":{"line":13,"column":13},"generated":{"line":1,"column":248}},{"source":"node_modules\\ol\\render\\replay.js","name":"CIRCLE","original":{"line":13,"column":13},"generated":{"line":1,"column":256}},{"source":"node_modules\\ol\\render\\replay.js","name":"ReplayType","original":{"line":14,"column":2},"generated":{"line":1,"column":263}},{"source":"node_modules\\ol\\render\\replay.js","name":"LINE_STRING","original":{"line":14,"column":13},"generated":{"line":1,"column":265}},{"source":"node_modules\\ol\\render\\replay.js","name":"LINE_STRING","original":{"line":14,"column":13},"generated":{"line":1,"column":273}},{"source":"node_modules\\ol\\render\\replay.js","name":"ReplayType","original":{"line":15,"column":2},"generated":{"line":1,"column":285}},{"source":"node_modules\\ol\\render\\replay.js","name":"IMAGE","original":{"line":15,"column":13},"generated":{"line":1,"column":287}},{"source":"node_modules\\ol\\render\\replay.js","name":"IMAGE","original":{"line":15,"column":13},"generated":{"line":1,"column":295}},{"source":"node_modules\\ol\\render\\replay.js","name":"ReplayType","original":{"line":16,"column":2},"generated":{"line":1,"column":301}},{"source":"node_modules\\ol\\render\\replay.js","name":"TEXT","original":{"line":16,"column":13},"generated":{"line":1,"column":303}},{"source":"node_modules\\ol\\render\\replay.js","name":"TEXT","original":{"line":16,"column":13},"generated":{"line":1,"column":311}},{"source":"node_modules\\ol\\render\\replay.js","name":"ReplayType","original":{"line":17,"column":2},"generated":{"line":1,"column":316}},{"source":"node_modules\\ol\\render\\replay.js","name":"DEFAULT","original":{"line":17,"column":13},"generated":{"line":1,"column":318}},{"source":"node_modules\\ol\\render\\replay.js","name":"DEFAULT","original":{"line":17,"column":13},"generated":{"line":1,"column":326}},{"source":"node_modules\\ol\\render\\replay.js","name":"TEXT_ALIGN","original":{"line":24,"column":11},"generated":{"line":1,"column":335}},{"source":"node_modules\\ol\\render\\replay.js","original":{"line":24,"column":24},"generated":{"line":1,"column":337}},{"source":"node_modules\\ol\\render\\replay.js","original":{"line":24,"column":24},"generated":{"line":1,"column":345}},{"source":"node_modules\\ol\\render\\replay.js","original":{"line":24,"column":24},"generated":{"line":1,"column":356}},{"source":"node_modules\\ol\\render\\replay.js","name":"TEXT_ALIGN","original":{"line":25,"column":0},"generated":{"line":1,"column":359}},{"source":"node_modules\\ol\\render\\replay.js","original":{"line":25,"column":0},"generated":{"line":1,"column":361}},{"source":"node_modules\\ol\\render\\replay.js","original":{"line":25,"column":21},"generated":{"line":1,"column":366}},{"source":"node_modules\\ol\\render\\replay.js","name":"TEXT_ALIGN","original":{"line":26,"column":0},"generated":{"line":1,"column":368}},{"source":"node_modules\\ol\\render\\replay.js","original":{"line":26,"column":0},"generated":{"line":1,"column":370}},{"source":"node_modules\\ol\\render\\replay.js","original":{"line":26,"column":20},"generated":{"line":1,"column":374}},{"source":"node_modules\\ol\\render\\replay.js","name":"TEXT_ALIGN","original":{"line":27,"column":0},"generated":{"line":1,"column":376}},{"source":"node_modules\\ol\\render\\replay.js","original":{"line":27,"column":0},"generated":{"line":1,"column":378}},{"source":"node_modules\\ol\\render\\replay.js","original":{"line":27,"column":23},"generated":{"line":1,"column":385}},{"source":"node_modules\\ol\\render\\replay.js","name":"TEXT_ALIGN","original":{"line":28,"column":0},"generated":{"line":1,"column":388}},{"source":"node_modules\\ol\\render\\replay.js","original":{"line":28,"column":0},"generated":{"line":1,"column":390}},{"source":"node_modules\\ol\\render\\replay.js","original":{"line":28,"column":22},"generated":{"line":1,"column":396}},{"source":"node_modules\\ol\\render\\replay.js","name":"TEXT_ALIGN","original":{"line":29,"column":0},"generated":{"line":1,"column":398}},{"source":"node_modules\\ol\\render\\replay.js","original":{"line":29,"column":0},"generated":{"line":1,"column":400}},{"source":"node_modules\\ol\\render\\replay.js","original":{"line":29,"column":22},"generated":{"line":1,"column":406}},{"source":"node_modules\\ol\\render\\replay.js","name":"TEXT_ALIGN","original":{"line":30,"column":0},"generated":{"line":1,"column":408}},{"source":"node_modules\\ol\\render\\replay.js","original":{"line":30,"column":0},"generated":{"line":1,"column":410}},{"source":"node_modules\\ol\\render\\replay.js","original":{"line":30,"column":20},"generated":{"line":1,"column":414}},{"source":"node_modules\\ol\\render\\replay.js","name":"TEXT_ALIGN","original":{"line":31,"column":0},"generated":{"line":1,"column":416}},{"source":"node_modules\\ol\\render\\replay.js","original":{"line":31,"column":0},"generated":{"line":1,"column":418}},{"source":"node_modules\\ol\\render\\replay.js","original":{"line":31,"column":23},"generated":{"line":1,"column":425}},{"source":"node_modules\\ol\\render\\replay.js","name":"TEXT_ALIGN","original":{"line":32,"column":0},"generated":{"line":1,"column":428}},{"source":"node_modules\\ol\\render\\replay.js","original":{"line":32,"column":0},"generated":{"line":1,"column":430}},{"source":"node_modules\\ol\\render\\replay.js","original":{"line":32,"column":24},"generated":{"line":1,"column":438}},{"source":"node_modules\\ol\\render\\replay.js","name":"TEXT_ALIGN","original":{"line":33,"column":0},"generated":{"line":1,"column":441}},{"source":"node_modules\\ol\\render\\replay.js","original":{"line":33,"column":0},"generated":{"line":1,"column":443}},{"source":"node_modules\\ol\\render\\replay.js","original":{"line":33,"column":27},"generated":{"line":1,"column":454}},{"source":"node_modules\\ol\\render\\replay.js","name":"TEXT_ALIGN","original":{"line":34,"column":0},"generated":{"line":1,"column":457}},{"source":"node_modules\\ol\\render\\replay.js","original":{"line":34,"column":0},"generated":{"line":1,"column":459}},{"source":"node_modules\\ol\\render\\replay.js","original":{"line":34,"column":28},"generated":{"line":1,"column":471}},{"source":"node_modules\\ol\\render\\replay.js","name":"TEXT_ALIGN","original":{"line":35,"column":0},"generated":{"line":1,"column":474}},{"source":"node_modules\\ol\\render\\replay.js","original":{"line":35,"column":0},"generated":{"line":1,"column":476}},{"source":"node_modules\\ol\\render\\replay.js","original":{"line":35,"column":23},"generated":{"line":1,"column":483}}],"sources":{"node_modules\\ol\\render\\replay.js":"/**\n * @module ol/render/replay\n */\nimport ReplayType from '../render/ReplayType.js';\n\n\n/**\n * @const\n * @type {Array.<module:ol/render/ReplayType>}\n */\nexport var ORDER = [\n  ReplayType.POLYGON,\n  ReplayType.CIRCLE,\n  ReplayType.LINE_STRING,\n  ReplayType.IMAGE,\n  ReplayType.TEXT,\n  ReplayType.DEFAULT\n];\n\n/**\n * @const\n * @enum {number}\n */\nexport var TEXT_ALIGN = {};\nTEXT_ALIGN['left'] = 0;\nTEXT_ALIGN['end'] = 0;\nTEXT_ALIGN['center'] = 0.5;\nTEXT_ALIGN['right'] = 1;\nTEXT_ALIGN['start'] = 1;\nTEXT_ALIGN['top'] = 0;\nTEXT_ALIGN['middle'] = 0.5;\nTEXT_ALIGN['hanging'] = 0.2;\nTEXT_ALIGN['alphabetic'] = 0.8;\nTEXT_ALIGN['ideographic'] = 0.8;\nTEXT_ALIGN['bottom'] = 1;\n\n//# sourceMappingURL=replay.js.map"},"lineCount":null}},"hash":"30a0207326e3391bb570cd7f3c6953b4","cacheData":{"env":{}}}