{"id":"index.html","dependencies":[{"name":"C:\\Users\\kaan.akturk\\Desktop\\Weather Condition of Turkey on Map\\ClientSide\\package.json","includedInParent":true,"mtime":1535698623540},{"name":"./index.js","dynamic":true,"parent":"C:\\Users\\kaan.akturk\\Desktop\\Weather Condition of Turkey on Map\\ClientSide\\index.html","resolved":"C:\\Users\\kaan.akturk\\Desktop\\Weather Condition of Turkey on Map\\ClientSide\\index.js"}],"generated":{"html":"<!DOCTYPE html>\r\n<html>\r\n  <head>\r\n    <meta charset=\"utf-8\">\r\n    <title>Weather Conditions Map in Turkey</title>\r\n    <style>\r\n      #map {\r\n        height: 100%;\r\n        width: 100%;\r\n        position: absolute;\r\n        top: 0px;\r\n        bottom: 0px;\r\n        right: 0px;\r\n        left: 0px;\r\n      }\r\n      .cities {\r\n        top: 1%;\r\n        position: absolute;\r\n        background-color: rgb(0,0,0,0.2);\r\n        -webkit-filter: drop-shadow(0 1px 4px rgba(0,0,0,0.2));\r\n        filter: drop-shadow(0 1px 4px rgba(0,0,0,0.2));\r\n        padding: 10px;\r\n        border-radius: 12px;\r\n        border: 2px solid #f7e707;\r\n        bottom: 5px;\r\n        text-align: center;\r\n        left: -10px;\r\n        width:  60px; \r\n        visibility: hidden;\r\n      }\r\n      .cities:after, .cities:before {\r\n        \r\n      top: 97%;\r\n      border: solid transparent;\r\n      content: \" \";\r\n      height: 0;\r\n      width: 0;\r\n      position: absolute;\r\n      pointer-events: none;\r\n    }\r\n    .cities:after {\r\n      border-top-color: rgb(0,0,0,0.2);\r\n      border-width: 5px;\r\n      left: 24px;\r\n      margin-left: -10px;\r\n    }\r\n    .cities:before {\r\n      border-top-color: rgb(0,0,0,0.2);\r\n      border-width: 5px;\r\n      left: 24px;\r\n      margin-left: -10px;\r\n    }\r\n\r\n      \r\n    </style>\r\n  </head>\r\n  <body>\r\n    <div id=\"map\"></div>\r\n    <div id=\"popup\"></div>\r\n    \r\n    <script src=\"https://ajax.googleapis.com/ajax/libs/jquery/2.1.1/jquery.min.js\"></script>\r\n    <script src=\"http://code.jquery.com/jquery-1.11.3.min.js\"></script>\r\n    <script src=\"https://ajax.googleapis.com/ajax/libs/jquery/3.1.0/jquery.min.js\"></script>\r\n    <script src=\"https://maxcdn.bootstrapcdn.com/bootstrap/3.3.7/js/bootstrap.min.js\"></script>\r\n    <script src=\"/1eb2fea9c2117ff23fa2d3e1e96462bd.js\"></script>\r\n    \r\n  </body>\r\n</html>"},"hash":"ef78a7ac05b2b62d5a3c87353d4b93e1","cacheData":{}}